[
	{
		"inputs": [
			{
				"internalType": "uint256",
				"name": "_projectId",
				"type": "uint256"
			}
		],
		"name": "acceptAsset",
		"outputs": [],
		"stateMutability": "nonpayable",
		"type": "function"
	},
	{
		"inputs": [
			{
				"internalType": "uint256",
				"name": "_projectId",
				"type": "uint256"
			}
		],
		"name": "acceptProject",
		"outputs": [],
		"stateMutability": "nonpayable",
		"type": "function"
	},
	{
		"inputs": [
			{
				"internalType": "uint256",
				"name": "_projectId",
				"type": "uint256"
			}
		],
		"name": "addFunds",
		"outputs": [],
		"stateMutability": "payable",
		"type": "function"
	},
	{
		"inputs": [],
		"stateMutability": "nonpayable",
		"type": "constructor"
	},
	{
		"anonymous": false,
		"inputs": [
			{
				"indexed": false,
				"internalType": "uint256",
				"name": "projectId",
				"type": "uint256"
			}
		],
		"name": "AssetAccepted",
		"type": "event"
	},
	{
		"anonymous": false,
		"inputs": [
			{
				"indexed": false,
				"internalType": "uint256",
				"name": "projectId",
				"type": "uint256"
			},
			{
				"indexed": false,
				"internalType": "uint8",
				"name": "rejectionCount",
				"type": "uint8"
			}
		],
		"name": "AssetRejected",
		"type": "event"
	},
	{
		"anonymous": false,
		"inputs": [
			{
				"indexed": false,
				"internalType": "uint256",
				"name": "projectId",
				"type": "uint256"
			}
		],
		"name": "AssetSubmitted",
		"type": "event"
	},
	{
		"inputs": [
			{
				"internalType": "address payable",
				"name": "_buyer",
				"type": "address"
			},
			{
				"internalType": "address payable",
				"name": "_seller",
				"type": "address"
			}
		],
		"name": "createProject",
		"outputs": [
			{
				"internalType": "uint256",
				"name": "",
				"type": "uint256"
			}
		],
		"stateMutability": "nonpayable",
		"type": "function"
	},
	{
		"anonymous": false,
		"inputs": [
			{
				"indexed": false,
				"internalType": "uint256",
				"name": "projectId",
				"type": "uint256"
			}
		],
		"name": "DisputeEscalated",
		"type": "event"
	},
	{
		"anonymous": false,
		"inputs": [
			{
				"indexed": false,
				"internalType": "uint256",
				"name": "projectId",
				"type": "uint256"
			},
			{
				"indexed": false,
				"internalType": "bool",
				"name": "acceptedBySeller",
				"type": "bool"
			}
		],
		"name": "DisputeResolved",
		"type": "event"
	},
	{
		"anonymous": false,
		"inputs": [
			{
				"indexed": false,
				"internalType": "uint256",
				"name": "projectId",
				"type": "uint256"
			},
			{
				"indexed": false,
				"internalType": "address",
				"name": "recipient",
				"type": "address"
			},
			{
				"indexed": false,
				"internalType": "uint256",
				"name": "amount",
				"type": "uint256"
			}
		],
		"name": "FundsTransferred",
		"type": "event"
	},
	{
		"anonymous": false,
		"inputs": [
			{
				"indexed": false,
				"internalType": "uint256",
				"name": "projectId",
				"type": "uint256"
			},
			{
				"indexed": false,
				"internalType": "uint256",
				"name": "amount",
				"type": "uint256"
			}
		],
		"name": "PaymentReceived",
		"type": "event"
	},
	{
		"anonymous": false,
		"inputs": [
			{
				"indexed": false,
				"internalType": "uint256",
				"name": "projectId",
				"type": "uint256"
			},
			{
				"indexed": false,
				"internalType": "address",
				"name": "participant",
				"type": "address"
			},
			{
				"indexed": false,
				"internalType": "enum Escrow.Role",
				"name": "role",
				"type": "uint8"
			}
		],
		"name": "ProjectAccepted",
		"type": "event"
	},
	{
		"anonymous": false,
		"inputs": [
			{
				"indexed": false,
				"internalType": "uint256",
				"name": "projectId",
				"type": "uint256"
			},
			{
				"indexed": false,
				"internalType": "address",
				"name": "buyer",
				"type": "address"
			},
			{
				"indexed": false,
				"internalType": "address",
				"name": "seller",
				"type": "address"
			}
		],
		"name": "ProjectCreated",
		"type": "event"
	},
	{
		"inputs": [
			{
				"internalType": "uint256",
				"name": "_projectId",
				"type": "uint256"
			}
		],
		"name": "rejectAsset",
		"outputs": [],
		"stateMutability": "nonpayable",
		"type": "function"
	},
	{
		"inputs": [
			{
				"internalType": "uint256",
				"name": "_projectId",
				"type": "uint256"
			},
			{
				"internalType": "bool",
				"name": "_acceptAsset",
				"type": "bool"
			}
		],
		"name": "resolveDispute",
		"outputs": [],
		"stateMutability": "nonpayable",
		"type": "function"
	},
	{
		"inputs": [
			{
				"internalType": "uint256",
				"name": "_projectId",
				"type": "uint256"
			},
			{
				"internalType": "string",
				"name": "_assetLink",
				"type": "string"
			},
			{
				"internalType": "string",
				"name": "_instructions",
				"type": "string"
			}
		],
		"name": "submitAsset",
		"outputs": [],
		"stateMutability": "nonpayable",
		"type": "function"
	},
	{
		"inputs": [
			{
				"internalType": "uint256",
				"name": "_projectId",
				"type": "uint256"
			}
		],
		"name": "getAssetInfo",
		"outputs": [
			{
				"internalType": "string",
				"name": "",
				"type": "string"
			},
			{
				"internalType": "string",
				"name": "",
				"type": "string"
			}
		],
		"stateMutability": "view",
		"type": "function"
	},
	{
		"inputs": [
			{
				"internalType": "uint256",
				"name": "_projectId",
				"type": "uint256"
			}
		],
		"name": "getProjectAmount",
		"outputs": [
			{
				"internalType": "uint256",
				"name": "",
				"type": "uint256"
			}
		],
		"stateMutability": "view",
		"type": "function"
	},
	{
		"inputs": [
			{
				"internalType": "address",
				"name": "_user",
				"type": "address"
			}
		],
		"name": "getProjectsForApproval",
		"outputs": [
			{
				"internalType": "uint256[]",
				"name": "",
				"type": "uint256[]"
			}
		],
		"stateMutability": "view",
		"type": "function"
	},
	{
		"inputs": [
			{
				"internalType": "uint256",
				"name": "_projectId",
				"type": "uint256"
			}
		],
		"name": "getProjectStatus",
		"outputs": [
			{
				"internalType": "enum Escrow.Status",
				"name": "",
				"type": "uint8"
			}
		],
		"stateMutability": "view",
		"type": "function"
	},
	{
		"inputs": [
			{
				"internalType": "uint256",
				"name": "_projectId",
				"type": "uint256"
			}
		],
		"name": "getRejectionCount",
		"outputs": [
			{
				"internalType": "uint8",
				"name": "",
				"type": "uint8"
			}
		],
		"stateMutability": "view",
		"type": "function"
	},
	{
		"inputs": [
			{
				"internalType": "address",
				"name": "_user",
				"type": "address"
			}
		],
		"name": "getUserProjects",
		"outputs": [
			{
				"components": [
					{
						"internalType": "uint256",
						"name": "projectId",
						"type": "uint256"
					},
					{
						"internalType": "address",
						"name": "buyer",
						"type": "address"
					},
					{
						"internalType": "address",
						"name": "seller",
						"type": "address"
					},
					{
						"internalType": "enum Escrow.Status",
						"name": "status",
						"type": "uint8"
					},
					{
						"internalType": "bool",
						"name": "buyerAccepted",
						"type": "bool"
					},
					{
						"internalType": "bool",
						"name": "sellerAccepted",
						"type": "bool"
					},
					{
						"internalType": "uint256",
						"name": "amount",
						"type": "uint256"
					},
					{
						"internalType": "string",
						"name": "assetLink",
						"type": "string"
					},
					{
						"internalType": "string",
						"name": "instructions",
						"type": "string"
					},
					{
						"internalType": "uint8",
						"name": "rejectionCount",
						"type": "uint8"
					}
				],
				"internalType": "struct Escrow.ProjectDetails[]",
				"name": "",
				"type": "tuple[]"
			}
		],
		"stateMutability": "view",
		"type": "function"
	},
	{
		"inputs": [],
		"name": "owner",
		"outputs": [
			{
				"internalType": "address",
				"name": "",
				"type": "address"
			}
		],
		"stateMutability": "view",
		"type": "function"
	},
	{
		"inputs": [],
		"name": "projectCount",
		"outputs": [
			{
				"internalType": "uint256",
				"name": "",
				"type": "uint256"
			}
		],
		"stateMutability": "view",
		"type": "function"
	},
	{
		"inputs": [
			{
				"internalType": "uint256",
				"name": "",
				"type": "uint256"
			}
		],
		"name": "projects",
		"outputs": [
			{
				"internalType": "address payable",
				"name": "buyer",
				"type": "address"
			},
			{
				"internalType": "address payable",
				"name": "seller",
				"type": "address"
			},
			{
				"internalType": "enum Escrow.Status",
				"name": "status",
				"type": "uint8"
			},
			{
				"internalType": "bool",
				"name": "buyerAccepted",
				"type": "bool"
			},
			{
				"internalType": "bool",
				"name": "sellerAccepted",
				"type": "bool"
			},
			{
				"internalType": "uint256",
				"name": "amount",
				"type": "uint256"
			},
			{
				"components": [
					{
						"internalType": "string",
						"name": "assetLink",
						"type": "string"
					},
					{
						"internalType": "string",
						"name": "instructions",
						"type": "string"
					}
				],
				"internalType": "struct Escrow.AssetInfo",
				"name": "asset",
				"type": "tuple"
			},
			{
				"internalType": "uint8",
				"name": "rejectionCount",
				"type": "uint8"
			}
		],
		"stateMutability": "view",
		"type": "function"
	}
]